waveline/__init__.py
waveline/_common.py
waveline/datatypes.py
waveline/linwave.py
waveline/spotwave.py
waveline/utils.py
waveline-0.10.0.dist-info/METADATA
waveline-0.10.0.dist-info/WHEEL
waveline-0.10.0.dist-info/licenses/LICENSE.txt
waveline-0.10.0.dist-info/RECORD
