Metadata-Version: 2.4
Name: waveline
Version: 0.10.0
Summary: Library to easily interface with Vallen Systeme WaveLine™ devices
Project-URL: Changelog, https://github.com/vallen-systems/pyWaveLine/blob/master/CHANGELOG.md
Project-URL: Source, https://github.com/vallen-systems/pyWaveLine
Project-URL: Issues, https://github.com/vallen-systems/pyWaveLine/issues
Author-email: Lukas Berbuer <software@vallen.de>
License: MIT License
License-File: LICENSE.txt
Keywords: acoustic emission,conditionwave,data acquisition,linwave,spotwave,ultrasonic,vallen,waveline
Classifier: Development Status :: 4 - Beta
Classifier: Intended Audience :: Science/Research
Classifier: License :: OSI Approved :: MIT License
Classifier: Operating System :: OS Independent
Classifier: Programming Language :: Python :: 3
Classifier: Programming Language :: Python :: 3.7
Classifier: Programming Language :: Python :: 3.8
Classifier: Programming Language :: Python :: 3.9
Classifier: Programming Language :: Python :: 3.10
Classifier: Programming Language :: Python :: 3.11
Classifier: Programming Language :: Python :: 3.12
Classifier: Programming Language :: Python :: 3.13
Classifier: Topic :: Scientific/Engineering
Classifier: Topic :: Software Development
Classifier: Topic :: Software Development :: Libraries
Requires-Python: >=3.7
Requires-Dist: numpy
Requires-Dist: pyserial>=3
Provides-Extra: dev
Requires-Dist: asyncmock>=0.4.2; (python_version < '3.8') and extra == 'dev'
Requires-Dist: coverage[toml]>=5; extra == 'dev'
Requires-Dist: freezegun; extra == 'dev'
Requires-Dist: furo; extra == 'dev'
Requires-Dist: mypy>=0.9; extra == 'dev'
Requires-Dist: myst-parser; extra == 'dev'
Requires-Dist: pytest-asyncio; extra == 'dev'
Requires-Dist: pytest-benchmark; extra == 'dev'
Requires-Dist: pytest-repeat; extra == 'dev'
Requires-Dist: pytest>=6; extra == 'dev'
Requires-Dist: ruff~=0.3; extra == 'dev'
Requires-Dist: sphinx-autodoc-typehints; extra == 'dev'
Requires-Dist: sphinx>=5; extra == 'dev'
Requires-Dist: tox>=3.4; extra == 'dev'
Provides-Extra: docs
Requires-Dist: furo; extra == 'docs'
Requires-Dist: myst-parser; extra == 'docs'
Requires-Dist: sphinx-autodoc-typehints; extra == 'docs'
Requires-Dist: sphinx>=5; extra == 'docs'
Provides-Extra: tests
Requires-Dist: asyncmock>=0.4.2; (python_version < '3.8') and extra == 'tests'
Requires-Dist: coverage[toml]>=5; extra == 'tests'
Requires-Dist: freezegun; extra == 'tests'
Requires-Dist: pytest-asyncio; extra == 'tests'
Requires-Dist: pytest-benchmark; extra == 'tests'
Requires-Dist: pytest-repeat; extra == 'tests'
Requires-Dist: pytest>=6; extra == 'tests'
Provides-Extra: tools
Requires-Dist: mypy>=0.9; extra == 'tools'
Requires-Dist: ruff~=0.3; extra == 'tools'
Requires-Dist: tox>=3.4; extra == 'tools'
